smsto/__init__.py
smsto/exceptions.py
smsto/utils.py
smsto/affiliate/__init__.py
smsto/authentication/__init__.py
smsto/contacts/__init__.py
smsto/hlr/__init__.py
smsto/legacy/__init__.py
smsto/mnp/__init__.py
smsto/shortlinks/__init__.py
smsto/sms/__init__.py
smsto/sms/models.py
smsto/team/__init__.py
smsto/viber/__init__.py
smsto-0.0.2.dist-info/METADATA
smsto-0.0.2.dist-info/WHEEL
smsto-0.0.2.dist-info/top_level.txt
smsto-0.0.2.dist-info/RECORD
